common/__init__.py
common/task.py
common/util.py
parser/__init__.py
parser/joyparser.py
parser/zeekparser.py
tlsfeatmark-0.1.dist-info/LICENSE
tlsfeatmark-0.1.dist-info/METADATA
tlsfeatmark-0.1.dist-info/WHEEL
tlsfeatmark-0.1.dist-info/top_level.txt
tlsfeatmark-0.1.dist-info/RECORD
