Metadata-Version: 2.1
Name: tlsfeatmark
Version: 0.1
Summary: a benchmark tool for Joy and Zeek
Home-page: https://github.com/zliucd/tlsfeatmark
Author: Zhi Liu
Author-email: zliucd66@gmail.com
License: UNKNOWN
Platform: UNKNOWN
Classifier: Programming Language :: Python :: 3
Classifier: License :: OSI Approved :: MIT License
Classifier: Operating System :: OS Independent
Requires-Dist: py-cpuinfo (>=8.0.0)
